pydrama/__init__.py
pydrama/main.py
pydrama/data/ansible_roles.txt
pydrama/data/ansible_tasks.txt
pydrama/data/boot_hooks.txt
pydrama/data/bootlog.txt
pydrama/data/cfiles.txt
pydrama/data/composer.txt
pydrama/data/docker_packages.txt
pydrama/data/docker_tags.txt
pydrama/data/messages.txt
pydrama/data/os_releases.txt
pydrama/data/packages.txt
pydrama/data/rkhunter_checks.txt
pydrama/data/rkhunter_rootkits.txt
pydrama/data/rkhunter_tasks.txt
pydrama/data/simcity.txt
pydrama/modules/__init__.py
pydrama/modules/ansible.py
pydrama/modules/bootlog.py
pydrama/modules/cc.py
pydrama/modules/data.py
pydrama/modules/docker_build.py
pydrama/modules/download.py
pydrama/modules/ocr_train.py
pydrama/modules/pip_install.py
pydrama/modules/weblog.py
pydrama-0.1.5.dist-info/LICENSE
pydrama-0.1.5.dist-info/METADATA
pydrama-0.1.5.dist-info/WHEEL
pydrama-0.1.5.dist-info/entry_points.txt
pydrama-0.1.5.dist-info/top_level.txt
pydrama-0.1.5.dist-info/RECORD
