Metadata-Version: 2.1
Name: pydrama
Version: 0.1.5
Summary: A Python programmer's tool for showing off / slacking off
Home-page: https://github.com/eaobservatory/pydrama
Author: JimEverest
Author-email: ttqwer1@163.com
Classifier: Programming Language :: Python :: 3
Classifier: License :: OSI Approved :: MIT License
Classifier: Operating System :: OS Independent
Requires-Python: >=3.6
License-File: LICENSE
